cpu-main.v
module ballLocator(randInt, location);
  input[6:0] randInt;
  output reg[2:0] location;

  // Integer used for the clock:
  integer i;

  // Location is incremented by 1 for each "1" in randInt:
  always @(randInt) begin
    location = 0;
    for (i=0;i<7;i=i+1) begin
      if (randInt[i] == 1'b1) begin
        location = location + 1;
      end
    end
  end
endmodule

module plinkoboard(clk,rst,randChoice,count1,count2,count3,count4,count5,count6,count7,count8,ballLocation);
  input clk, rst;
  input[6:0] randChoice;
  output [4:0] count1, count2, count3, count4, count5, count6, count7, count8;

  // Takes the value inputed in randChoice and puts the location that the ball falls in into a wire named ballLoc:
  ballLocator ball0(randChoice,ballLoc);
  wire[2:0] ballLoc;

  // Assigns ballLoc to the output ballLocation:
  output[2:0] ballLocation;
  assign ballLocation = ballLoc;

  // Creates a 5-bit register for each of the locations that the ball can fall in:
  reg [4:0] counts[0:7];

  // Integer used for the clock:
  integer i;

  // If reset is 0, all of the count registers are reset back to 0. At the positive edge of the clock, the counter at location ballLoc is incremented by 1.
  always @(posedge clk) begin
    if (rst) begin
      for (i=0; i<8; i++) begin
        counts[i] = 0;
      end
    end else begin
      counts[ballLoc] = counts[ballLoc] + 1;
    end
  end

  // Assigns counts 1-8 to the corresponding counts register;
  assign count1 = counts[0];
  assign count2 = counts[1];
  assign count3 = counts[2];
  assign count4 = counts[3];
  assign count5 = counts[4];
  assign count6 = counts[5];
  assign count7 = counts[6];
  assign count8 = counts[7];
endmodule

testbenches/testbench.v
`define STRINGIFY(DEFINE) $sformatf("%0s", `"DEFINE`")

`define assert(assertion) \
  if (!(assertion)) begin \
    $display("ASSERTION FAILED in %m: %s", `STRINGIFY(assertion)); \
    $fatal; \
end

module plinkotb;
  // Clocking and control
  reg clk, rst;
  reg[6:0] randChoice;
  wire[4:0] count1,count2,count3,count4,count5,count6,count7,count8;
  wire[2:0] ballLocation;

  reg[6:0] randInt;
  wire[2:0] location;

  integer i,j,k;

  plinkoboard plinkoboard0(clk,rst,randChoice,count1,count2,count3,count4,count5,count6,count7,count8,ballLocation);
  ballLocator locator0(randInt, location);

  initial begin
    $dumpfile("build/tb-processor.vcd");  // Dump waveforms to file 'dump.vcd'
    $dumpvars;

    // Any time there's a change in output signals, output them to log
    $monitor("Time=%03tms, Clock=%b, Reset=%b, RandChoice=%b, Count1=%d, Count2=%d, Count3=%d, Count4=%d, Count5=%d, Count6=%d, Count7=%d, Count8=%d, BallLocation=%d", $time, clk, rst, randChoice, count1, count2, count3, count4, count5, count6, count7, count8, ballLocation);

    // Resets all of the counters:
    rst = 1; clk =0; #10;

    // Does one clock cycle while setting reset to 0;
    clk=1; #10;
    clk=0; rst=0; #10;

    // Generates 80 random numbers:
    for (i = 0; i < 80; i++) begin
      randChoice = $random % 127;

      // Clock Cycles:
      clk = ~clk; #10;
      clk = ~clk; #10;
    end

    // Outputs one bar for each ball that has fallen in Count 1:
    $write("\nCount1 = %02d: ",count1);
    for (j = 0; j<count1; j++) begin
      $write("| ");
    end

    // Outputs one bar for each ball that has fallen in Count 2:
    $write("\nCount2 = %02d: ",count2);
    for (j = 0; j<count2; j++) begin
      $write("| ");
    end

    // Outputs one bar for each ball that has fallen in Count 3:
    $write("\nCount3 = %02d: ",count3);
    for (j = 0; j<count3; j++) begin
      $write("| ");
    end

    // Outputs one bar for each ball that has fallen in Count 4:
    $write("\nCount4 = %02d: ",count4);
    for (j = 0; j<count4; j++) begin
      $write("| ");
    end

    // Outputs one bar for each ball that has fallen in Count 5:
    $write("\nCount5 = %02d: ",count5);
    for (j = 0; j<count5; j++) begin
      $write("| ");
    end
    
    // Outputs one bar for each ball that has fallen in Count 6:
    $write("\nCount6 = %02d: ",count6);
    for (j = 0; j<count6; j++) begin
      $write("| ");
    end

    // Outputs one bar for each ball that has fallen in Count 7:
    $write("\nCount7 = %02d: ",count7);
    for (j = 0; j<count7; j++) begin
      $write("| ");
    end

    // Outputs one bar for each ball that has fallen in Count 8:
    $write("\nCount8 = %02d: ",count8);
    for (j = 0; j<count8; j++) begin
      $write("| ");
    end
    
  end
endmodule

build/tb-processor.vcd
$date
	Sat Dec 16 22:40:10 2023
$end
$version
	Icarus Verilog
$end
$timescale
	1s
$end
$scope module plinkotb $end
$var wire 3 ! location [2:0] $end
$var wire 5 " count8 [4:0] $end
$var wire 5 # count7 [4:0] $end
$var wire 5 $ count6 [4:0] $end
$var wire 5 % count5 [4:0] $end
$var wire 5 & count4 [4:0] $end
$var wire 5 ' count3 [4:0] $end
$var wire 5 ( count2 [4:0] $end
$var wire 5 ) count1 [4:0] $end
$var wire 3 * ballLocation [2:0] $end
$var reg 1 + clk $end
$var reg 7 , randChoice [6:0] $end
$var reg 7 - randInt [6:0] $end
$var reg 1 . rst $end
$var integer 32 / i [31:0] $end
$var integer 32 0 j [31:0] $end
$scope module locator0 $end
$var wire 7 1 randInt [6:0] $end
$var reg 3 2 location [2:0] $end
$var integer 32 3 i [31:0] $end
$upscope $end
$scope module plinkoboard0 $end
$var wire 3 4 ballLocation [2:0] $end
$var wire 1 + clk $end
$var wire 5 5 count1 [4:0] $end
$var wire 5 6 count2 [4:0] $end
$var wire 5 7 count3 [4:0] $end
$var wire 5 8 count4 [4:0] $end
$var wire 5 9 count5 [4:0] $end
$var wire 5 : count6 [4:0] $end
$var wire 5 ; count7 [4:0] $end
$var wire 5 < count8 [4:0] $end
$var wire 7 = randChoice [6:0] $end
$var wire 1 . rst $end
$var wire 3 > ballLoc [2:0] $end
$var integer 32 ? i [31:0] $end
$scope module ball0 $end
$var wire 7 @ randInt [6:0] $end
$var reg 3 A location [2:0] $end
$var integer 32 B i [31:0] $end
$upscope $end
$upscope $end
$upscope $end
$enddefinitions $end
#0
$dumpvars
bx B
bx A
bx @
bx ?
bx >
bx =
bx <
bx ;
bx :
bx 9
bx 8
bx 7
bx 6
bx 5
bx 4
bx 3
bx 2
bx 1
bx 0
bx /
1.
bx -
bx ,
0+
bx *
bx )
bx (
bx '
bx &
bx %
bx $
bx #
bx "
bx !
$end
#10
b0 "
b0 <
b0 #
b0 ;
b0 $
b0 :
b0 %
b0 9
b0 &
b0 8
b0 '
b0 7
b0 (
b0 6
b0 )
b0 5
b1000 ?
1+
#20
0.
0+
#30
b1 %
b1 9
b111 B
b100 *
b100 4
b100 >
b100 A
1+
b1110100 ,
b1110100 =
b1110100 @
b0 /
#40
0+
#50
b1 &
b1 8
b111 B
b11 *
b11 4
b11 >
b11 A
1+
b1100100 ,
b1100100 =
b1100100 @
b1 /
#60
0+
#70
b10 %
b10 9
b111 B
b100 *
b100 4
b100 >
b100 A
1+
b1100101 ,
b1100101 =
b1100101 @
b10 /
#80
0+
#90
b11 %
b11 9
b111 B
b100 *
b100 4
b100 >
b100 A
1+
b1011100 ,
b1011100 =
b1011100 @
b11 /
#100
0+
#110
b1 $
b1 :
b111 B
b101 *
b101 4
b101 >
b101 A
1+
b11111 ,
b11111 =
b11111 @
b100 /
#120
0+
#130
b10 $
b10 :
b111 B
b101 *
b101 4
b101 >
b101 A
1+
b1111001 ,
b1111001 =
b1111001 @
b101 /
#140
0+
#150
b1 '
b1 7
b111 B
b10 *
b10 4
b10 >
b10 A
1+
b1010 ,
b1010 =
b1010 @
b110 /
#160
0+
#170
b100 %
b100 9
b111 B
b100 *
b100 4
b100 >
b100 A
1+
b1010110 ,
b1010110 =
b1010110 @
b111 /
#180
0+
#190
b101 %
b101 9
b111 B
b100 *
b100 4
b100 >
b100 A
1+
b11110 ,
b11110 =
b11110 @
b1000 /
#200
0+
#210
b11 $
b11 :
b111 B
b101 *
b101 4
b101 >
b101 A
1+
b111101 ,
b111101 =
b111101 @
b1001 /
#220
0+
#230
b10 &
b10 8
b111 B
b11 *
b11 4
b11 >
b11 A
1+
b1000101 ,
b1000101 =
b1000101 @
b1010 /
#240
0+
#250
b10 '
b10 7
b111 B
b10 *
b10 4
b10 >
b10 A
1+
b101 ,
b101 =
b101 @
b1011 /
#260
0+
#270
b11 &
b11 8
b111 B
b11 *
b11 4
b11 >
b11 A
1+
b101100 ,
b101100 =
b101100 @
b1100 /
#280
0+
#290
b100 &
b100 8
b111 B
b11 *
b11 4
b11 >
b11 A
1+
b1101000 ,
b1101000 =
b1101000 @
b1101 /
#300
0+
#310
b101 &
b101 8
b111 B
b11 *
b11 4
b11 >
b11 A
1+
b110100 ,
b110100 =
b110100 @
b1110 /
#320
0+
#330
b11 '
b11 7
b111 B
b10 *
b10 4
b10 >
b10 A
1+
b101 ,
b101 =
b101 @
b1111 /
#340
0+
#350
b110 &
b110 8
b111 B
b11 *
b11 4
b11 >
b11 A
1+
b1000011 ,
b1000011 =
b1000011 @
b10000 /
#360
0+
#370
b111 &
b111 8
b111 B
b11 *
b11 4
b11 >
b11 A
1+
b1000101 ,
b1000101 =
b1000101 @
b10001 /
#380
0+
#390
b1000 &
b1000 8
b111 B
b11 *
b11 4
b11 >
b11 A
1+
b110001 ,
b110001 =
b110001 @
b10010 /
#400
0+
#410
b1 )
b1 5
b111 B
b0 *
b0 4
b0 >
b0 A
1+
b0 ,
b0 =
b0 @
b10011 /
#420
0+
#430
b1001 &
b1001 8
b11 *
b11 4
b11 >
b11 A
b111 B
1+
b1001100 ,
b1001100 =
b1001100 @
b10100 /
#440
0+
#450
b100 $
b100 :
b111 B
b101 *
b101 4
b101 >
b101 A
1+
b111101 ,
b111101 =
b111101 @
b10101 /
#460
0+
#470
b1010 &
b1010 8
b111 B
b11 *
b11 4
b11 >
b11 A
1+
b1011000 ,
b1011000 =
b1011000 @
b10110 /
#480
0+
#490
b100 '
b100 7
b111 B
b10 *
b10 4
b10 >
b10 A
1+
b10001 ,
b10001 =
b10001 @
b10111 /
#500
0+
#510
b1 "
b1 <
b111 B
b111 *
b111 4
b111 >
b111 A
1+
b1111111 ,
b1111111 =
b1111111 @
b11000 /
#520
0+
#530
b101 '
b101 7
b111 B
b10 *
b10 4
b10 >
b10 A
1+
b100001 ,
b100001 =
b100001 @
b11001 /
#540
0+
#550
b1011 &
b1011 8
b111 B
b11 *
b11 4
b11 >
b11 A
1+
b1000101 ,
b1000101 =
b1000101 @
b11010 /
#560
0+
#570
b110 %
b110 9
b111 B
b100 *
b100 4
b100 >
b100 A
1+
b111010 ,
b111010 =
b111010 @
b11011 /
#580
0+
#590
b111 %
b111 9
1+
b11100 /
#600
0+
#610
b1 #
b1 ;
b111 B
b110 *
b110 4
b110 >
b110 A
1+
b1011111 ,
b1011111 =
b1011111 @
b11101 /
#620
0+
#630
b1100 &
b1100 8
b111 B
b11 *
b11 4
b11 >
b11 A
1+
b1110000 ,
b1110000 =
b1110000 @
b11110 /
#640
0+
#650
b110 '
b110 7
b111 B
b10 *
b10 4
b10 >
b10 A
1+
b10010 ,
b10010 =
b10010 @
b11111 /
#660
0+
#670
b111 '
b111 7
b111 B
b10 *
b10 4
b10 >
b10 A
1+
b110000 ,
b110000 =
b110000 @
b100000 /
#680
0+
#690
b101 $
b101 :
b111 B
b101 *
b101 4
b101 >
b101 A
1+
b1110110 ,
b1110110 =
b1110110 @
b100001 /
#700
0+
#710
b1000 %
b1000 9
b111 B
b100 *
b100 4
b100 >
b100 A
1+
b1000111 ,
b1000111 =
b1000111 @
b100010 /
#720
0+
#730
b110 $
b110 :
b111 B
b101 *
b101 4
b101 >
b101 A
1+
b1011101 ,
b1011101 =
b1011101 @
b100011 /
#740
0+
#750
b1001 %
b1001 9
b111 B
b100 *
b100 4
b100 >
b100 A
1+
b1101010 ,
b1101010 =
b1101010 @
b100100 /
#760
0+
#770
b111 $
b111 :
b111 B
b101 *
b101 4
b101 >
b101 A
1+
b1010111 ,
b1010111 =
b1010111 @
b100101 /
#780
0+
#790
b1010 %
b1010 9
b111 B
b100 *
b100 4
b100 >
b100 A
1+
b11101 ,
b11101 =
b11101 @
b100110 /
#800
0+
#810
b1000 $
b1000 :
b111 B
b101 *
b101 4
b101 >
b101 A
1+
b1100111 ,
b1100111 =
b1100111 @
b100111 /
#820
0+
#830
b1011 %
b1011 9
b111 B
b100 *
b100 4
b100 >
b100 A
1+
b1010101 ,
b1010101 =
b1010101 @
b101000 /
#840
0+
#850
b1000 '
b1000 7
b111 B
b10 *
b10 4
b10 >
b10 A
1+
b11000 ,
b11000 =
b11000 @
b101001 /
#860
0+
#870
b1100 %
b1100 9
b111 B
b100 *
b100 4
b100 >
b100 A
1+
b1110100 ,
b1110100 =
b1110100 @
b101010 /
#880
0+
#890
b1001 $
b1001 :
b111 B
b101 *
b101 4
b101 >
b101 A
1+
b111101 ,
b111101 =
b111101 @
b101011 /
#900
0+
#910
b1010 $
b1010 :
b111 B
b101 *
b101 4
b101 >
b101 A
1+
b1100111 ,
b1100111 =
b1100111 @
b101100 /
#920
0+
#930
b1 (
b1 6
b111 B
b1 *
b1 4
b1 >
b1 A
1+
b1000 ,
b1000 =
b1000 @
b101101 /
#940
0+
#950
b1101 %
b1101 9
b111 B
b100 *
b100 4
b100 >
b100 A
1+
b1010011 ,
b1010011 =
b1010011 @
b101110 /
#960
0+
#970
b1001 '
b1001 7
b111 B
b10 *
b10 4
b10 >
b10 A
1+
b100010 ,
b100010 =
b100010 @
b101111 /
#980
0+
#990
b1110 %
b1110 9
b111 B
b100 *
b100 4
b100 >
b100 A
1+
b1010110 ,
b1010110 =
b1010110 @
b110000 /
#1000
0+
#1010
b1010 '
b1010 7
b111 B
b10 *
b10 4
b10 >
b10 A
1+
b110 ,
b110 =
b110 @
b110001 /
#1020
0+
#1030
b1111 %
b1111 9
b111 B
b100 *
b100 4
b100 >
b100 A
1+
b1100011 ,
b1100011 =
b1100011 @
b110010 /
#1040
0+
#1050
b1101 &
b1101 8
b111 B
b11 *
b11 4
b11 >
b11 A
1+
b110100 ,
b110100 =
b110100 @
b110011 /
#1060
0+
#1070
b1011 '
b1011 7
b111 B
b10 *
b10 4
b10 >
b10 A
1+
b1000010 ,
b1000010 =
b1000010 @
b110100 /
#1080
0+
#1090
b1100 '
b1100 7
b111 B
b10 *
b10 4
b10 >
b10 A
1+
b1010000 ,
b1010000 =
b1010000 @
b110101 /
#1100
0+
#1110
b10000 %
b10000 9
b111 B
b100 *
b100 4
b100 >
b100 A
1+
b1000111 ,
b1000111 =
b1000111 @
b110110 /
#1120
0+
#1130
b10 #
b10 ;
b111 B
b110 *
b110 4
b110 >
b110 A
1+
b1110111 ,
b1110111 =
b1110111 @
b110111 /
#1140
0+
#1150
b1101 '
b1101 7
b111 B
b10 *
b10 4
b10 >
b10 A
1+
b1010000 ,
b1010000 =
b1010000 @
b111000 /
#1160
0+
#1170
b1110 &
b1110 8
b111 B
b11 *
b11 4
b11 >
b11 A
1+
b1101000 ,
b1101000 =
b1101000 @
b111001 /
#1180
0+
#1190
b1110 '
b1110 7
b111 B
b10 *
b10 4
b10 >
b10 A
1+
b1010 ,
b1010 =
b1010 @
b111010 /
#1200
0+
#1210
b1011 $
b1011 :
b111 B
b101 *
b101 4
b101 >
b101 A
1+
b1100111 ,
b1100111 =
b1100111 @
b111011 /
#1220
0+
#1230
b10 (
b10 6
b111 B
b1 *
b1 4
b1 >
b1 A
1+
b1000 ,
b1000 =
b1000 @
b111100 /
#1240
0+
#1250
b10001 %
b10001 9
b111 B
b100 *
b100 4
b100 >
b100 A
1+
b1001101 ,
b1001101 =
b1001101 @
b111101 /
#1260
0+
#1270
b1111 &
b1111 8
b111 B
b11 *
b11 4
b11 >
b11 A
1+
b1000101 ,
b1000101 =
b1000101 @
b111110 /
#1280
0+
#1290
b10000 &
b10000 8
b111 B
b11 *
b11 4
b11 >
b11 A
1+
b1110 ,
b1110 =
b1110 @
b111111 /
#1300
0+
#1310
b10010 %
b10010 9
b111 B
b100 *
b100 4
b100 >
b100 A
1+
b1101100 ,
b1101100 =
b1101100 @
b1000000 /
#1320
0+
#1330
b1111 '
b1111 7
b111 B
b10 *
b10 4
b10 >
b10 A
1+
b101 ,
b101 =
b101 @
b1000001 /
#1340
0+
#1350
b10001 &
b10001 8
b111 B
b11 *
b11 4
b11 >
b11 A
1+
b10110 ,
b10110 =
b10110 @
b1000010 /
#1360
0+
#1370
b10010 &
b10010 8
b111 B
b11 *
b11 4
b11 >
b11 A
1+
b100011 ,
b100011 =
b100011 @
b1000011 /
#1380
0+
#1390
b10011 %
b10011 9
b111 B
b100 *
b100 4
b100 >
b100 A
1+
b1100101 ,
b1100101 =
b1100101 @
b1000100 /
#1400
0+
#1410
b10011 &
b10011 8
b111 B
b11 *
b11 4
b11 >
b11 A
1+
b101010 ,
b101010 =
b101010 @
b1000101 /
#1420
0+
#1430
b1100 $
b1100 :
b111 B
b101 *
b101 4
b101 >
b101 A
1+
b1011101 ,
b1011101 =
b1011101 @
b1000110 /
#1440
0+
#1450
b10100 %
b10100 9
b111 B
b100 *
b100 4
b100 >
b100 A
1+
b1001101 ,
b1001101 =
b1001101 @
b1000111 /
#1460
0+
#1470
b10000 '
b10000 7
b111 B
b10 *
b10 4
b10 >
b10 A
1+
b1001 ,
b1001 =
b1001 @
b1001000 /
#1480
0+
#1490
b10101 %
b10101 9
b111 B
b100 *
b100 4
b100 >
b100 A
1+
b1001110 ,
b1001110 =
b1001110 @
b1001001 /
#1500
0+
#1510
b10100 &
b10100 8
b111 B
b11 *
b11 4
b11 >
b11 A
1+
b1010001 ,
b1010001 =
b1010001 @
b1001010 /
#1520
0+
#1530
b1101 $
b1101 :
b111 B
b101 *
b101 4
b101 >
b101 A
1+
b1111010 ,
b1111010 =
b1111010 @
b1001011 /
#1540
0+
#1550
b1110 $
b1110 :
b111 B
b101 *
b101 4
b101 >
b101 A
1+
b1101101 ,
b1101101 =
b1101101 @
b1001100 /
#1560
0+
#1570
b10101 &
b10101 8
b111 B
b11 *
b11 4
b11 >
b11 A
1+
b1011 ,
b1011 =
b1011 @
b1001101 /
#1580
0+
#1590
b10110 %
b10110 9
b111 B
b100 *
b100 4
b100 >
b100 A
1+
b1011001 ,
b1011001 =
b1011001 @
b1001110 /
#1600
0+
#1610
b10111 %
b10111 9
b111 B
b100 *
b100 4
b100 >
b100 A
1+
b1101010 ,
b1101010 =
b1101010 @
b1001111 /
#1620
0+
#1630
b1 0
b1010000 /
